CHANGELOG.md
todo_client/__init__.py
todo_client/cli.py
todo_client/core/__init__.py
todo_client/core/constants.py
todo_client/core/helpers.py
todo_client/core/logging_config.py
todo_client/core/repl.py
todo_client/core/tasks.py
todo_client/example.py
todo_client-0.1.0.dist-info/LICENSE
todo_client-0.1.0.dist-info/METADATA
todo_client-0.1.0.dist-info/WHEEL
todo_client-0.1.0.dist-info/entry_points.txt
todo_client-0.1.0.dist-info/RECORD
