Metadata-Version: 2.1
Name: todo-client
Version: 0.1.0
Summary: A todo client with CLI and REPL interfaces.
Home-page: https://github.com/rmkane/todo-client
License: MIT
Keywords: todo,client,cli,repl
Author: Ryan Kane
Author-email: rmkane@proton.me
Requires-Python: >=3.9,<4.0
Classifier: Development Status :: 3 - Alpha
Classifier: Intended Audience :: Developers
Classifier: License :: OSI Approved :: MIT License
Classifier: Operating System :: OS Independent
Classifier: Programming Language :: Python :: 3
Classifier: Programming Language :: Python :: 3.9
Classifier: Programming Language :: Python :: 3.10
Classifier: Programming Language :: Python :: 3.11
Classifier: Programming Language :: Python :: 3.12
Classifier: Topic :: Software Development :: Build Tools
Requires-Dist: PyYAML (>=6.0.1,<7.0.0)
Project-URL: Documentation, https://github.com/rmkane/todo-client
Project-URL: Repository, https://github.com/rmkane/todo-client
